{
  "gitSyncId": "652449ce5012274cbc5158f5_652449cf5012274cbc515913",
  "id": "Contacts_DeleteQuery",
  "pluginId": "postgres-plugin",
  "pluginType": "DB",
  "unpublishedAction": {
    "actionConfiguration": {
      "body": "DELETE FROM public.\"contacts\"\n  WHERE \"id\" = {{data_table.triggeredRow.id}};",
      "encodeParamsToggle": true,
      "paginationType": "NONE",
      "pluginSpecifiedTemplates": [
        {
          "value": true
        }
      ],
      "timeoutInMillisecond": 10000
    },
    "confirmBeforeExecute": false,
    "datasource": {
      "id": "supabase",
      "isAutoGenerated": false,
      "name": "supabase",
      "pluginId": "postgres-plugin"
    },
    "name": "DeleteQuery",
    "pageId": "Contacts",
    "runBehaviour": "MANUAL",
    "userSetOnLoad": false
  }
}